hybgensea/__init__.py
hybgensea/hybgensea.py
hybgensea/libhgscvrp.dll
hybgensea/tests/__init__.py
hybgensea/tests/test_cvrp.py
hybgensea/tests/test_tsp.py
hybgensea-0.0.1.dist-info/METADATA
hybgensea-0.0.1.dist-info/WHEEL
hybgensea-0.0.1.dist-info/licenses/LICENSE
hybgensea-0.0.1.dist-info/RECORD
