Metadata-Version: 2.2
Name: hybgensea
Version: 0.0.1
Summary: Wrapper for the Hybrid Genetic Search algorithm for Capacitated Vehicle Routing Problems (HGS-CVRP)
Author: Changhyun Kwon
Requires-Python: >=3.10
